onelogin/__init__.py
onelogin/saml2/__init__.py
onelogin/saml2/artifact_resolve.py
onelogin/saml2/artifact_response.py
onelogin/saml2/auth.py
onelogin/saml2/authn_request.py
onelogin/saml2/compat.py
onelogin/saml2/constants.py
onelogin/saml2/crypto_utils.py
onelogin/saml2/errors.py
onelogin/saml2/idp_metadata_parser.py
onelogin/saml2/logout_request.py
onelogin/saml2/logout_response.py
onelogin/saml2/metadata.py
onelogin/saml2/response.py
onelogin/saml2/schemas/access_control-xacml-2.0-context-schema-os.xsd
onelogin/saml2/schemas/access_control-xacml-2.0-policy-schema-os.xsd
onelogin/saml2/schemas/access_control-xacml-2.0-saml-assertion-schema-os.xsd
onelogin/saml2/schemas/access_control-xacml-2.0-saml-protocol-schema-os.xsd
onelogin/saml2/schemas/saml-schema-assertion-2.0.xsd
onelogin/saml2/schemas/saml-schema-authn-context-2.0.xsd
onelogin/saml2/schemas/saml-schema-authn-context-types-2.0.xsd
onelogin/saml2/schemas/saml-schema-metadata-2.0.xsd
onelogin/saml2/schemas/saml-schema-protocol-2.0.xsd
onelogin/saml2/schemas/sstc-metadata-attr.xsd
onelogin/saml2/schemas/sstc-saml-attribute-ext.xsd
onelogin/saml2/schemas/sstc-saml-metadata-algsupport-v1.0.xsd
onelogin/saml2/schemas/sstc-saml-metadata-ui-v1.0.xsd
onelogin/saml2/schemas/sstc-saml-schema-assertion-2.0.xsd
onelogin/saml2/schemas/sstc-saml-schema-protocol-2.0.xsd
onelogin/saml2/schemas/xenc-schema.xsd
onelogin/saml2/schemas/xml.xsd
onelogin/saml2/schemas/xmldsig-core-schema.xsd
onelogin/saml2/settings.py
onelogin/saml2/soap_logout_request.py
onelogin/saml2/ssl_adapter.py
onelogin/saml2/utils.py
onelogin/saml2/xml_templates.py
onelogin/saml2/xml_utils.py
onelogin/saml2/xmlparser.py
maykin_python3_saml-1.16.1.dist-info/LICENSE
maykin_python3_saml-1.16.1.dist-info/METADATA
maykin_python3_saml-1.16.1.dist-info/WHEEL
maykin_python3_saml-1.16.1.dist-info/RECORD
