Metadata-Version: 2.1
Name: maykin-python3-saml
Version: 1.16.1
Summary: Saml Python Toolkit. Add SAML support to your Python software using this library
Home-page: https://github.com/maykinmedia/python3-saml
License: Apache-2.0
Keywords: saml,saml2,sso,xmlsec,federation,identity
Author: SAML-Toolkits
Author-email: contact@iamdigitalservices.com
Maintainer: Sixto Martin
Maintainer-email: sixto.martin.garcia@gmail.com
Requires-Python: >=2.7, !=3.0.*, !=3.1.*, !=3.2.*, !=3.3.*, !=3.4.*
Classifier: License :: OSI Approved :: Apache Software License
Classifier: Programming Language :: Python :: 2
Classifier: Programming Language :: Python :: 2.7
Classifier: Programming Language :: Python :: 3
Classifier: Programming Language :: Python :: 3.5
Classifier: Programming Language :: Python :: 3.6
Classifier: Programming Language :: Python :: 3.7
Classifier: Programming Language :: Python :: 3.8
Classifier: Programming Language :: Python :: 3.9
Classifier: Programming Language :: Python :: 3.10
Classifier: Programming Language :: Python :: 3.11
Classifier: Programming Language :: Python :: 3.12
Classifier: Topic :: Software Development :: Build Tools
Classifier: Topic :: Software Development :: Libraries :: Python Modules
Provides-Extra: test
Requires-Dist: coverage (>=4.5.2) ; extra == "test"
Requires-Dist: cryptography (>=40.0.0)
Requires-Dist: flake8 (>=3.6.0,<=5.0.0) ; extra == "test"
Requires-Dist: freezegun (>=0.3.11,<=1.1.0) ; extra == "test"
Requires-Dist: isodate (>=0.6.1)
Requires-Dist: lxml (>=4.7.1)
Requires-Dist: pytest (>=4.6.11) ; extra == "test"
Requires-Dist: requests (>=2.24.0)
Requires-Dist: requests-mock (>=1.9.3) ; extra == "test"
Requires-Dist: responses (>=0.12.0) ; extra == "test"
Requires-Dist: xmlsec (>=1.3.9)
Project-URL: Bug Tracker, https://github.com/SAML-Toolkits/python3-saml/issues
Project-URL: Repository, https://github.com/maykinmedia/python3-saml
